README.txt
setup.cfg
setup.py
connect4/__init__.py
connect4.egg-info/PKG-INFO
connect4.egg-info/SOURCES.txt
connect4.egg-info/dependency_links.txt
connect4.egg-info/top_level.txt
connect4/gui/__init__.py
connect4/gui/gui.py
connect4/logic/AI.py
connect4/logic/__init__.py
connect4/logic/game.py
connect4/utils/__init__.py
connect4/utils/tree.py