Metadata-Version: 1.1
Name: connect4
Version: 0.0.3
Summary: connect 4
Home-page: https://github.com/reutsharabani/N-in-a-row
Author: Reut Sharabani
Author-email: reut.sharabani@gmail.com
License: MIT
Keywords: games,board games
Platform: UNKNOWN
Classifier: Development Status :: 2 - Pre-Alpha
Classifier: Intended Audience :: End Users/Desktop
Classifier: Topic :: Games/Entertainment :: Board Games
Classifier: License :: OSI Approved :: MIT License
Classifier: Programming Language :: Python :: 2
Classifier: Programming Language :: Python :: 2.6
Classifier: Programming Language :: Python :: 2.7
